deepai-text-generation/__init__.py
deepai-text-generation/text_generator.py
deepai_text_generation/__init__.py
deepai_text_generation/text_generator.py
simple-gpt2/__init__.py
simple-gpt2/text_generator.py
simple_gpt2-1.0.0.dist-info/LICENSE
simple_gpt2-1.0.0.dist-info/METADATA
simple_gpt2-1.0.0.dist-info/WHEEL
simple_gpt2-1.0.0.dist-info/top_level.txt
simple_gpt2-1.0.0.dist-info/RECORD
