Metadata-Version: 2.1
Name: simple-gpt2
Version: 1.0.0
Summary: Wrapper of the DeepAI GPT-2 text generation API.
Home-page: https://github.com/ajivoin/simple-gpt2
Author: Andrew Jivoin
Author-email: andrew+py@jivoin.com
License: UNKNOWN
Project-URL: Bug Tracker, https://github.com/ajivoin/simple-gpt2/issues
Platform: UNKNOWN
Classifier: Programming Language :: Python :: 3
Classifier: License :: OSI Approved :: The Unlicense (Unlicense)
Classifier: Operating System :: OS Independent
Requires-Python: >=3.6
